scepreq/__init__.py
scepreq/asn1.py
scepreq/builders.py
scepreq/certificate.py
scepreq/client.py
scepreq/crl.py
scepreq/cryptoutils.py
scepreq/enums.py
scepreq/envelope.py
scepreq/main.py
scepreq/message.py
scepreq/privatekey.py
scepreq/publickey.py
scepreq/responses.py
scepreq/signingrequest.py
scepreq-0.1.1.dist-info/licenses/LICENSE
scepreq-0.1.1.dist-info/METADATA
scepreq-0.1.1.dist-info/WHEEL
scepreq-0.1.1.dist-info/entry_points.txt
scepreq-0.1.1.dist-info/top_level.txt
scepreq-0.1.1.dist-info/RECORD
